pysensu/__init__.py
pysensu/api.py
pysensu_ng-0.13.0.dist-info/AUTHORS.rst
pysensu_ng-0.13.0.dist-info/LICENSE
pysensu_ng-0.13.0.dist-info/METADATA
pysensu_ng-0.13.0.dist-info/WHEEL
pysensu_ng-0.13.0.dist-info/top_level.txt
pysensu_ng-0.13.0.dist-info/RECORD
